mm_proxy/__init__.py
mm_proxy/check.py
mm_proxy/parsing.py
mm_proxy/public_services.py
mm_proxy/py.typed
mm_proxy-0.0.2.dist-info/METADATA
mm_proxy-0.0.2.dist-info/WHEEL
mm_proxy-0.0.2.dist-info/RECORD
