Metadata-Version: 2.4
Name: mm-proxy
Version: 0.0.2
Summary: Proxy utilities
License: Proprietary
Classifier: Development Status :: 4 - Beta
Classifier: Intended Audience :: Developers
Classifier: License :: Other/Proprietary License
Classifier: Programming Language :: Python :: 3.13
Classifier: Typing :: Typed
Requires-Python: >=3.13
Requires-Dist: mm-http~=0.2.4
